wsfinder/__init__.py
wsfinder/main.py
word_scramble-1.1.0.dist-info/LICENSE
word_scramble-1.1.0.dist-info/METADATA
word_scramble-1.1.0.dist-info/WHEEL
word_scramble-1.1.0.dist-info/top_level.txt
word_scramble-1.1.0.dist-info/RECORD
