Metadata-Version: 2.1
Name: word-scramble
Version: 1.1.0
Summary: Python 3+ version scrabble word finder! Super efficient with hashtables!
Home-page: https://github.com/Harvard90873/word-scramble
Author: Harvard90873
Author-email: harvard90873@gmail.com
License: MIT
Platform: UNKNOWN
Classifier: License :: OSI Approved :: MIT License
Classifier: Programming Language :: Python :: 3.9
Classifier: Programming Language :: Python :: 3
Requires-Dist: python-algorithms-3x
Requires-Dist: termcolor
Requires-Dist: and-or-not
Requires-Dist: data-structures3x
Requires-Dist: spell-checker
